analytics_zoo_serving-0.11.2.data/scripts/cluster-serving-cli
analytics_zoo_serving-0.11.2.data/scripts/cluster-serving-init
analytics_zoo_serving-0.11.2.data/scripts/cluster-serving-py-setup.py
analytics_zoo_serving-0.11.2.data/scripts/cluster-serving-restart
analytics_zoo_serving-0.11.2.data/scripts/cluster-serving-shutdown
analytics_zoo_serving-0.11.2.data/scripts/cluster-serving-start
analytics_zoo_serving-0.11.2.data/scripts/cluster-serving-stop
analytics_zoo_serving-0.11.2.data/scripts/cluster-with-numactl.sh
analytics_zoo_serving-0.11.2.data/scripts/config.yaml
analytics_zoo_serving-0.11.2.data/scripts/download-serving-jar.sh
zoo/conf/cluster-serving-py-setup.py
zoo/conf/config.yaml
zoo/serving/client.py
zoo/serving/env.py
zoo/serving/schema.py
analytics_zoo_serving-0.11.2.dist-info/METADATA
analytics_zoo_serving-0.11.2.dist-info/WHEEL
analytics_zoo_serving-0.11.2.dist-info/top_level.txt
analytics_zoo_serving-0.11.2.dist-info/RECORD
