Metadata-Version: 2.1
Name: analytics-zoo-serving
Version: 0.11.2
Summary: A unified Data Analytics and AI platform for distributed TensorFlow, Keras, PyTorch, Apache Spark/Flink and Ray
Home-page: https://github.com/intel-analytics/analytics-zoo
Author: Analytics Zoo Authors
Author-email: bigdl-user-group@googlegroups.com
License: Apache License, Version 2.0
Platform: mac
Platform: linux
Classifier: License :: OSI Approved :: Apache Software License
Classifier: Programming Language :: Python :: 3
Classifier: Programming Language :: Python :: 3.5
Classifier: Programming Language :: Python :: 3.6
Classifier: Programming Language :: Python :: Implementation :: CPython
Requires-Dist: redis
Requires-Dist: pyyaml
Requires-Dist: httpx
Requires-Dist: pyarrow
Requires-Dist: opencv-python
